fastapi_clerk_auth/__init__.py
fastapi_clerk_auth-0.0.8.dist-info/licenses/LICENSE
fastapi_clerk_auth-0.0.8.dist-info/METADATA
fastapi_clerk_auth-0.0.8.dist-info/WHEEL
fastapi_clerk_auth-0.0.8.dist-info/top_level.txt
fastapi_clerk_auth-0.0.8.dist-info/RECORD
