Metadata-Version: 2.4
Name: fastapi_clerk_auth
Version: 0.0.8
Summary: FastAPI Auth Middleware for Clerk (https://clerk.com)
Author-email: OSS Mafia <dev@oss-mafia.com>
Project-URL: Homepage, https://github.com/OSSMafia/fastapi-clerk-middleware
Project-URL: Source, https://github.com/OSSMafia/fastapi-clerk-middleware
Keywords: fastapi,clerk,authentication,jwt
Classifier: Development Status :: 5 - Production/Stable
Classifier: Framework :: FastAPI
Classifier: Intended Audience :: Developers
Classifier: License :: OSI Approved :: MIT License
Classifier: Programming Language :: Python :: 3.9
Classifier: Programming Language :: Python :: 3.10
Classifier: Programming Language :: Python :: 3.11
Classifier: Programming Language :: Python :: 3.12
Requires-Python: >=3.9
License-File: LICENSE
Requires-Dist: fastapi>=0.95.0
Requires-Dist: PyJWT>=2.0.0
Requires-Dist: cryptography>=43.0.1
Provides-Extra: dev
Requires-Dist: ruff==0.2.0; extra == "dev"
Requires-Dist: pytest; extra == "dev"
Requires-Dist: pytest-asyncio; extra == "dev"
Requires-Dist: pytest-mock; extra == "dev"
Requires-Dist: bump2version; extra == "dev"
Dynamic: license-file
